pptestmarcinsiatkowski/__init__.py
pptestmarcinsiatkowski/m_mod_pptest.py
pptestmarcinsiatkowski-0.0.1.dist-info/LICENSE.txt
pptestmarcinsiatkowski-0.0.1.dist-info/METADATA
pptestmarcinsiatkowski-0.0.1.dist-info/WHEEL
pptestmarcinsiatkowski-0.0.1.dist-info/top_level.txt
pptestmarcinsiatkowski-0.0.1.dist-info/RECORD
