Metadata-Version: 2.1
Name: pptestmarcinsiatkowski
Version: 0.0.1
Summary: My test package
Author-email: MS <marcin.siatkowski@gmail.com>
License: MIT License
Keywords: pptestmarcinsiatkowski,funny functions,name,surname,personal data
Requires-Python: >=3.0
License-File: LICENSE.txt
Requires-Dist: numpy ; python_version >= "3.0"
